[
    {
        "code": "WCAG2AA.Principle4.Guideline4_1.4_1_2.H91.Button.Name",
        "type": "error",
        "typeCode": 1,
        "message": "This button element does not have a name available to an accessibility API. Valid names are: title undefined, element content, aria-label undefined, aria-labelledby undefined.",
        "context": "<button class=\"MuiButtonBase-root-48 MuiIconButton-root-191 DropDownMenu-icon-188\" tabindex=\"0\" type=\"button\" id=\"hv-dropdown-menu1-icon-button\" aria-haspopup=\"true\"><span class=\"MuiIconButton-labe...</button>",
        "selector": "#hv-dropdown-menu1-icon-button",
        "runner": "htmlcs",
        "runnerExtras": {}
    },
    {
        "code": "button-name",
        "type": "error",
        "typeCode": 1,
        "message": "Buttons must have discernible text (https://dequeuniversity.com/rules/axe/3.4/button-name?application=axeAPI)",
        "context": "<button class=\"MuiButtonBase-root-48 MuiIconButton-root-191 DropDownMenu-icon-188\" tabindex=\"0\" type=\"button\" id=\"hv-dropdown-menu1-icon-button\" aria-haspopup=\"true\"><span class=\"MuiIconButton-labe...</button>",
        "selector": "#hv-dropdown-menu1-icon-button",
        "runner": "axe",
        "runnerExtras": {
            "description": "Ensures buttons have discernible text",
            "impact": "critical",
            "help": "Buttons must have discernible text",
            "helpUrl": "https://dequeuniversity.com/rules/axe/3.4/button-name?application=axeAPI"
        }
    }
]
